[
  {
    "id": 1,
    "location": "Austin, TX",
    "image": "https://c1.wallpaperflare.com/preview/551/3/749/architecture-family-house-front-yard-garage-thumbnail.jpg",
    "properties": [
      {
        "id": "A",
        "title": "Modern Family Home",
        "price": "$450,000",
        "location": "Austin, TX",
        "bedrooms": 4,
        "bathrooms": 3,
        "size": "2,800 sq ft",
        "type": "Single Family",
        "image": "https://c1.wallpaperflare.com/preview/551/3/749/architecture-family-house-front-yard-garage-thumbnail.jpg",
        "description": "A spacious family home with modern amenities, open floor plan, and a large backyard.",
        "year_built": 2018,
        "contact": "contact@homesale.com"
      },
      {
        "id": "B",
        "title": "Luxury Villa",
        "price": "$850,000",
        "location": "Austin, TX",
        "bedrooms": 5,
        "bathrooms": 4,
        "size": "3,500 sq ft",
        "type": "Villa",
        "image": "https://wallpapercat.com/w/full/0/2/8/743826-1920x1080-desktop-1080p-house-wallpaper.jpg",
        "description": "A beautiful villa with a stunning design, swimming pool, and prime location.",
        "year_built": 2020,
        "contact": "luxury@homesale.com"
      },
      {
        "id": "C",
        "title": "Cozy Cottage",
        "price": "$300,000",
        "location": "Austin, TX",
        "bedrooms": 3,
        "bathrooms": 2,
        "size": "1,800 sq ft",
        "type": "Cottage",
        "image": "https://media.istockphoto.com/id/488120139/photo/modern-real-estate.jpg?s=612x612&w=0&k=20&c=88jk1VLSoYboMmLUx173sHs_XrZ9pH21as8lC7WINQs=",
        "description": "A charming cottage with vintage aesthetics and a large garden.",
        "year_built": 2015,
        "contact": "cozycottage@homesale.com"
      },
      {
        "id": "D",
        "title": "Urban Apartment",
        "price": "$200,000",
        "location": "Austin, TX",
        "bedrooms": 2,
        "bathrooms": 2,
        "size": "1,200 sq ft",
        "type": "Apartment",
        "image": "https://e0.pxfuel.com/wallpapers/361/35/desktop-wallpaper-vintage-victorian-in-chelsea-that-was-cut-into-apartments-is-restored-old-homes.jpg",
        "description": "A modern apartment located in the heart of the city with all conveniences.",
        "year_built": 2021,
        "contact": "urban@homesale.com"
      },
      {
        "id": "E",
        "title": "Suburban House",
        "price": "$400,000",
        "location": "Austin, TX",
        "bedrooms": 4,
        "bathrooms": 3,
        "size": "2,500 sq ft",
        "type": "Single Family",
        "image": "https://images.alphacoders.com/435/435117.jpg",
        "description": "A lovely suburban house with a spacious yard and modern kitchen.",
        "year_built": 2019,
        "contact": "suburban@homesale.com"
      },
      {
        "id": "F",
        "title": "Lakefront Property",
        "price": "$600,000",
        "location": "Austin, TX",
        "bedrooms": 4,
        "bathrooms": 3,
        "size": "3,000 sq ft",
        "type": "Villa",
        "image": "https://wallpapers.com/images/hd/dream-house-pictures-1600-x-900-u8uk7s3cjcqw3crs.jpg",
        "description": "A picturesque property with stunning lake views and private dock.",
        "year_built": 2017,
        "contact": "lakefront@homesale.com"
      }
    ]
  },
  {
    "id": 2,
    "location": "Dallas, TX",
    "image": "https://media.istockphoto.com/id/488120139/photo/modern-real-estate.jpg?s=612x612&w=0&k=20&c=88jk1VLSoYboMmLUx173sHs_XrZ9pH21as8lC7WINQs=",
    "properties": [
      {
        "id": "A",
        "title": "Modern Family Home",
        "price": "$450,000",
        "location": "Dallas, TX",
        "bedrooms": 4,
        "bathrooms": 3,
        "size": "2,800 sq ft",
        "type": "Single Family",
        "image": "https://media.istockphoto.com/id/488120139/photo/modern-real-estate.jpg?s=612x612&w=0&k=20&c=88jk1VLSoYboMmLUx173sHs_XrZ9pH21as8lC7WINQs=",
        "description": "A spacious family home with modern amenities, open floor plan, and a large backyard.",
        "year_built": 2018,
        "contact": "contact@homesale.com"
      },
      {
        "id": "B",
        "title": "Luxury Villa",
        "price": "$850,000",
        "location": "Dallas, TX",
        "bedrooms": 5,
        "bathrooms": 4,
        "size": "3,500 sq ft",
        "type": "Villa",
        "image": "https://c1.wallpaperflare.com/preview/551/3/749/architecture-family-house-front-yard-garage-thumbnail.jpg",
        "description": "A beautiful villa with a stunning design, swimming pool, and prime location.",
        "year_built": 2020,
        "contact": "luxury@homesale.com"
      },
      {
        "id": "C",
        "title": "Cozy Cottage",
        "price": "$300,000",
        "location": "Dallas, TX",
        "bedrooms": 3,
        "bathrooms": 2,
        "size": "1,800 sq ft",
        "type": "Cottage",
        "image": "https://e0.pxfuel.com/wallpapers/361/35/desktop-wallpaper-vintage-victorian-in-chelsea-that-was-cut-into-apartments-is-restored-old-homes.jpg",
        "description": "A charming cottage with vintage aesthetics and a large garden.",
        "year_built": 2015,
        "contact": "cozycottage@homesale.com"
      },
      {
        "id": "D",
        "title": "Urban Apartment",
        "price": "$200,000",
        "location": "Dallas, TX",
        "bedrooms": 2,
        "bathrooms": 2,
        "size": "1,200 sq ft",
        "type": "Apartment",
        "image": "https://images.alphacoders.com/435/435117.jpg",
        "description": "A modern apartment located in the heart of the city with all conveniences.",
        "year_built": 2021,
        "contact": "urban@homesale.com"
      },
      {
        "id": "E",
        "title": "Suburban House",
        "price": "$400,000",
        "location": "Dallas, TX",
        "bedrooms": 4,
        "bathrooms": 3,
        "size": "2,500 sq ft",
        "type": "Single Family",
        "image": "https://wallpapercat.com/w/full/0/2/8/743826-1920x1080-desktop-1080p-house-wallpaper.jpg",
        "description": "A lovely suburban house with a spacious yard and modern kitchen.",
        "year_built": 2019,
        "contact": "suburban@homesale.com"
      },
      {
        "id": "F",
        "title": "Lakefront Property",
        "price": "$600,000",
        "location": "Dallas, TX",
        "bedrooms": 4,
        "bathrooms": 3,
        "size": "3,000 sq ft",
        "type": "Villa",
        "image": "https://wallpapers.com/images/hd/dream-house-pictures-1600-x-900-u8uk7s3cjcqw3crs.jpg",
        "description": "A picturesque property with stunning lake views and private dock.",
        "year_built": 2017,
        "contact": "lakefront@homesale.com"
      }
    ]
  },
  {
    "id": 3,
    "location": "Houston, TX",
    "image": "https://e0.pxfuel.com/wallpapers/361/35/desktop-wallpaper-vintage-victorian-in-chelsea-that-was-cut-into-apartments-is-restored-old-homes.jpg",
    "properties": [
      {
        "id": "A",
        "title": "Modern Family Home",
        "price": "$450,000",
        "location": "Houston, TX",
        "bedrooms": 4,
        "bathrooms": 3,
        "size": "2,800 sq ft",
        "type": "Single Family",
        "image": "https://e0.pxfuel.com/wallpapers/361/35/desktop-wallpaper-vintage-victorian-in-chelsea-that-was-cut-into-apartments-is-restored-old-homes.jpg",
        "description": "A spacious family home with modern amenities, open floor plan, and a large backyard.",
        "year_built": 2018,
        "contact": "contact@homesale.com"
      },
      {
        "id": "B",
        "title": "Luxury Villa",
        "price": "$850,000",
        "location": "Houston, TX",
        "bedrooms": 5,
        "bathrooms": 4,
        "size": "3,500 sq ft",
        "type": "Villa",
        "image": "https://media.istockphoto.com/id/488120139/photo/modern-real-estate.jpg?s=612x612&w=0&k=20&c=88jk1VLSoYboMmLUx173sHs_XrZ9pH21as8lC7WINQs=",
        "description": "A beautiful villa with a stunning design, swimming pool, and prime location.",
        "year_built": 2020,
        "contact": "luxury@homesale.com"
      },
      {
        "id": "C",
        "title": "Cozy Cottage",
        "price": "$300,000",
        "location": "Houston, TX",
        "bedrooms": 3,
        "bathrooms": 2,
        "size": "1,800 sq ft",
        "type": "Cottage",
        "image": "https://wallpapercat.com/w/full/0/2/8/743826-1920x1080-desktop-1080p-house-wallpaper.jpg",
        "description": "A charming cottage with vintage aesthetics and a large garden.",
        "year_built": 2015,
        "contact": "cozycottage@homesale.com"
      },
      {
        "id": "D",
        "title": "Urban Apartment",
        "price": "$200,000",
        "location": "Houston, TX",
        "bedrooms": 2,
        "bathrooms": 2,
        "size": "1,200 sq ft",
        "type": "Apartment",
        "image": "https://c1.wallpaperflare.com/preview/551/3/749/architecture-family-house-front-yard-garage-thumbnail.jpg",
        "description": "A modern apartment located in the heart of the city with all conveniences.",
        "year_built": 2021,
        "contact": "urban@homesale.com"
      },
      {
        "id": "E",
        "title": "Suburban House",
        "price": "$400,000",
        "location": "Houston, TX",
        "bedrooms": 4,
        "bathrooms": 3,
        "size": "2,500 sq ft",
        "type": "Single Family",
        "image": "https://wallpapers.com/images/hd/dream-house-pictures-1600-x-900-u8uk7s3cjcqw3crs.jpg",
        "description": "A lovely suburban house with a spacious yard and modern kitchen.",
        "year_built": 2019,
        "contact": "suburban@homesale.com"
      },
      {
        "id": "F",
        "title": "Lakefront Property",
        "price": "$600,000",
        "location": "Houston, TX",
        "bedrooms": 4,
        "bathrooms": 3,
        "size": "3,000 sq ft",
        "type": "Villa",
        "image": "https://images.alphacoders.com/435/435117.jpg",
        "description": "A picturesque property with stunning lake views and private dock.",
        "year_built": 2017,
        "contact": "lakefront@homesale.com"
      }
    ]
  },
  {
    "id": 4,
    "location": "New York, NY",
    "image": "https://images.alphacoders.com/435/435117.jpg",
    "properties": [
      {
        "id": "A",
        "title": "Modern Family Home",
        "price": "$450,000",
        "location": "New York, NY",
        "bedrooms": 4,
        "bathrooms": 3,
        "size": "2,800 sq ft",
        "type": "Single Family",
        "image": "https://images.alphacoders.com/435/435117.jpg",
        "description": "A spacious family home with modern amenities, open floor plan, and a large backyard.",
        "year_built": 2018,
        "contact": "contact@homesale.com"
      },
      {
        "id": "B",
        "title": "Luxury Villa",
        "price": "$850,000",
        "location": "New York, NY",
        "bedrooms": 5,
        "bathrooms": 4,
        "size": "3,500 sq ft",
        "type": "Villa",
        "image": "https://e0.pxfuel.com/wallpapers/361/35/desktop-wallpaper-vintage-victorian-in-chelsea-that-was-cut-into-apartments-is-restored-old-homes.jpg",
        "description": "A beautiful villa with a stunning design, swimming pool, and prime location.",
        "year_built": 2020,
        "contact": "luxury@homesale.com"
      },
      {
        "id": "C",
        "title": "Cozy Cottage",
        "price": "$300,000",
        "location": "New York, NY",
        "bedrooms": 3,
        "bathrooms": 2,
        "size": "1,800 sq ft",
        "type": "Cottage",
        "image": "https://media.istockphoto.com/id/488120139/photo/modern-real-estate.jpg?s=612x612&w=0&k=20&c=88jk1VLSoYboMmLUx173sHs_XrZ9pH21as8lC7WINQs=",
        "description": "A charming cottage with vintage aesthetics and a large garden.",
        "year_built": 2015,
        "contact": "cozycottage@homesale.com"
      },
      {
        "id": "D",
        "title": "Urban Apartment",
        "price": "$200,000",
        "location": "New York, NY",
        "bedrooms": 2,
        "bathrooms": 2,
        "size": "1,200 sq ft",
        "type": "Apartment",
        "image": "https://wallpapercat.com/w/full/0/2/8/743826-1920x1080-desktop-1080p-house-wallpaper.jpg",
        "description": "A modern apartment located in the heart of the city with all conveniences.",
        "year_built": 2021,
        "contact": "urban@homesale.com"
      },
      {
        "id": "E",
        "title": "Suburban House",
        "price": "$400,000",
        "location": "New York, NY",
        "bedrooms": 4,
        "bathrooms": 3,
        "size": "2,500 sq ft",
        "type": "Single Family",
        "image": "https://c1.wallpaperflare.com/preview/551/3/749/architecture-family-house-front-yard-garage-thumbnail.jpg",
        "description": "A lovely suburban house with a spacious yard and modern kitchen.",
        "year_built": 2019,
        "contact": "suburban@homesale.com"
      },
      {
        "id": "F",
        "title": "Lakefront Property",
        "price": "$600,000",
        "location": "New York, NY",
        "bedrooms": 4,
        "bathrooms": 3,
        "size": "3,000 sq ft",
        "type": "Villa",
        "image": "https://wallpapers.com/images/hd/dream-house-pictures-1600-x-900-u8uk7s3cjcqw3crs.jpg",
        "description": "A picturesque property with stunning lake views and private dock.",
        "year_built": 2017,
        "contact": "lakefront@homesale.com"
      }
    ]
  },
  {
    "id": 5,
    "location": "Los Angeles, CA",
    "image": "https://wallpapercave.com/wp/wp3982670.jpg",
    "properties": [
      {
        "id": "A",
        "title": "Modern Family Home",
        "price": "$450,000",
        "location": "Los Angeles, CA",
        "bedrooms": 4,
        "bathrooms": 3,
        "size": "2,800 sq ft",
        "type": "Single Family",
        "image": "https://wallpapercave.com/wp/wp3982670.jpg",
        "description": "A spacious family home with modern amenities, open floor plan, and a large backyard.",
        "year_built": 2018,
        "contact": "contact@homesale.com"
      },
      {
        "id": "B",
        "title": "Luxury Villa",
        "price": "$850,000",
        "location": "Los Angeles, CA",
        "bedrooms": 5,
        "bathrooms": 4,
        "size": "3,500 sq ft",
        "type": "Villa",
        "image": "https://images.alphacoders.com/435/435117.jpg",
        "description": "A beautiful villa with a stunning design, swimming pool, and prime location.",
        "year_built": 2020,
        "contact": "luxury@homesale.com"
      },
      {
        "id": "C",
        "title": "Cozy Cottage",
        "price": "$300,000",
        "location": "Los Angeles, CA",
        "bedrooms": 3,
        "bathrooms": 2,
        "size": "1,800 sq ft",
        "type": "Cottage",
        "image": "https://wallpapercat.com/w/full/0/2/8/743826-1920x1080-desktop-1080p-house-wallpaper.jpg",
        "description": "A charming cottage with vintage aesthetics and a large garden.",
        "year_built": 2015,
        "contact": "cozycottage@homesale.com"
      },
      {
        "id": "D",
        "title": "Urban Apartment",
        "price": "$200,000",
        "location": "Los Angeles, CA",
        "bedrooms": 2,
        "bathrooms": 2,
        "size": "1,200 sq ft",
        "type": "Apartment",
        "image": "https://e0.pxfuel.com/wallpapers/361/35/desktop-wallpaper-vintage-victorian-in-chelsea-that-was-cut-into-apartments-is-restored-old-homes.jpg",
        "description": "A modern apartment located in the heart of the city with all conveniences.",
        "year_built": 2021,
        "contact": "urban@homesale.com"
      },
      {
        "id": "E",
        "title": "Suburban House",
        "price": "$400,000",
        "location": "Los Angeles, CA",
        "bedrooms": 4,
        "bathrooms": 3,
        "size": "2,500 sq ft",
        "type": "Single Family",
        "image": "https://c1.wallpaperflare.com/preview/551/3/749/architecture-family-house-front-yard-garage-thumbnail.jpg",
        "description": "A lovely suburban house with a spacious yard and modern kitchen.",
        "year_built": 2019,
        "contact": "suburban@homesale.com"
      },
      {
        "id": "F",
        "title": "Lakefront Property",
        "price": "$600,000",
        "location": "Los Angeles, CA",
        "bedrooms": 4,
        "bathrooms": 3,
        "size": "3,000 sq ft",
        "type": "Villa",
        "image": "https://media.istockphoto.com/id/488120139/photo/modern-real-estate.jpg?s=612x612&w=0&k=20&c=88jk1VLSoYboMmLUx173sHs_XrZ9pH21as8lC7WINQs=",
        "description": "A picturesque property with stunning lake views and private dock.",
        "year_built": 2017,
        "contact": "lakefront@homesale.com"
      }
    ]
  },
  {
    "id": 6,
    "location": "San Francisco, CA",
    "image": "https://wallpapers.com/images/hd/big-house-with-luscious-garden-ut1p7rgvzij6ptmu.jpg",
    "properties": [
      {
        "id": "A",
        "title": "Modern Family Home",
        "price": "$450,000",
        "location": "San Francisco, CA",
        "bedrooms": 4,
        "bathrooms": 3,
        "size": "2,800 sq ft",
        "type": "Single Family",
        "image": "https://wallpapers.com/images/hd/big-house-with-luscious-garden-ut1p7rgvzij6ptmu.jpg",
        "description": "A spacious family home with modern amenities, open floor plan, and a large backyard.",
        "year_built": 2018,
        "contact": "contact@homesale.com"
      },
      {
        "id": "B",
        "title": "Luxury Villa",
        "price": "$850,000",
        "location": "San Francisco, CA",
        "bedrooms": 5,
        "bathrooms": 4,
        "size": "3,500 sq ft",
        "type": "Villa",
        "image": "https://media.istockphoto.com/id/488120139/photo/modern-real-estate.jpg?s=612x612&w=0&k=20&c=88jk1VLSoYboMmLUx173sHs_XrZ9pH21as8lC7WINQs=",
        "description": "A beautiful villa with a stunning design, swimming pool, and prime location.",
        "year_built": 2020,
        "contact": "luxury@homesale.com"
      },
      {
        "id": "C",
        "title": "Cozy Cottage",
        "price": "$300,000",
        "location": "San Francisco, CA",
        "bedrooms": 3,
        "bathrooms": 2,
        "size": "1,800 sq ft",
        "type": "Cottage",
        "image": "https://c1.wallpaperflare.com/preview/551/3/749/architecture-family-house-front-yard-garage-thumbnail.jpg",
        "description": "A charming cottage with vintage aesthetics and a large garden.",
        "year_built": 2015,
        "contact": "cozycottage@homesale.com"
      },
      {
        "id": "D",
        "title": "Urban Apartment",
        "price": "$200,000",
        "location": "San Francisco, CA",
        "bedrooms": 2,
        "bathrooms": 2,
        "size": "1,200 sq ft",
        "type": "Apartment",
        "image": "https://images.alphacoders.com/435/435117.jpg",
        "description": "A modern apartment located in the heart of the city with all conveniences.",
        "year_built": 2021,
        "contact": "urban@homesale.com"
      },
      {
        "id": "E",
        "title": "Suburban House",
        "price": "$400,000",
        "location": "San Francisco, CA",
        "bedrooms": 4,
        "bathrooms": 3,
        "size": "2,500 sq ft",
        "type": "Single Family",
        "image": "https://wallpapercat.com/w/full/0/2/8/743826-1920x1080-desktop-1080p-house-wallpaper.jpg",
        "description": "A lovely suburban house with a spacious yard and modern kitchen.",
        "year_built": 2019,
        "contact": "suburban@homesale.com"
      },
      {
        "id": "F",
        "title": "Lakefront Property",
        "price": "$600,000",
        "location": "San Francisco, CA",
        "bedrooms": 4,
        "bathrooms": 3,
        "size": "3,000 sq ft",
        "type": "Villa",
        "image": "https://e0.pxfuel.com/wallpapers/361/35/desktop-wallpaper-vintage-victorian-in-chelsea-that-was-cut-into-apartments-is-restored-old-homes.jpg",
        "description": "A picturesque property with stunning lake views and private dock.",
        "year_built": 2017,
        "contact": "lakefront@homesale.com"
      }
    ]
  },
  {
    "id": 7,
    "location": "Denver, CO",
    "image": "https://e1.pxfuel.com/desktop-wallpaper/703/96/desktop-wallpaper-luxury-house-small-house-thumbnail.jpg",
    "properties": [
      {
        "id": "A",
        "title": "Modern Family Home",
        "price": "$450,000",
        "location": "Denver, CO",
        "bedrooms": 4,
        "bathrooms": 3,
        "size": "2,800 sq ft",
        "type": "Single Family",
        "image": "https://e1.pxfuel.com/desktop-wallpaper/703/96/desktop-wallpaper-luxury-house-small-house-thumbnail.jpg",
        "description": "A spacious family home with modern amenities, open floor plan, and a large backyard.",
        "year_built": 2018,
        "contact": "contact@homesale.com"
      },
      {
        "id": "B",
        "title": "Luxury Villa",
        "price": "$850,000",
        "location": "Denver, CO",
        "bedrooms": 5,
        "bathrooms": 4,
        "size": "3,500 sq ft",
        "type": "Villa",
        "image": "https://wallpapercat.com/w/full/0/2/8/743826-1920x1080-desktop-1080p-house-wallpaper.jpg",
        "description": "A beautiful villa with a stunning design, swimming pool, and prime location.",
        "year_built": 2020,
        "contact": "luxury@homesale.com"
      },
      {
        "id": "C",
        "title": "Cozy Cottage",
        "price": "$300,000",
        "location": "Denver, CO",
        "bedrooms": 3,
        "bathrooms": 2,
        "size": "1,800 sq ft",
        "type": "Cottage",
        "image": "https://media.istockphoto.com/id/488120139/photo/modern-real-estate.jpg?s=612x612&w=0&k=20&c=88jk1VLSoYboMmLUx173sHs_XrZ9pH21as8lC7WINQs=",
        "description": "A charming cottage with vintage aesthetics and a large garden.",
        "year_built": 2015,
        "contact": "cozycottage@homesale.com"
      },
      {
        "id": "D",
        "title": "Urban Apartment",
        "price": "$200,000",
        "location": "Denver, CO",
        "bedrooms": 2,
        "bathrooms": 2,
        "size": "1,200 sq ft",
        "type": "Apartment",
        "image": "https://e0.pxfuel.com/wallpapers/361/35/desktop-wallpaper-vintage-victorian-in-chelsea-that-was-cut-into-apartments-is-restored-old-homes.jpg",
        "description": "A modern apartment located in the heart of the city with all conveniences.",
        "year_built": 2021,
        "contact": "urban@homesale.com"
      },
      {
        "id": "E",
        "title": "Suburban House",
        "price": "$400,000",
        "location": "Denver, CO",
        "bedrooms": 4,
        "bathrooms": 3,
        "size": "2,500 sq ft",
        "type": "Single Family",
        "image": "https://images.alphacoders.com/435/435117.jpg",
        "description": "A lovely suburban house with a spacious yard and modern kitchen.",
        "year_built": 2019,
        "contact": "suburban@homesale.com"
      },
      {
        "id": "F",
        "title": "Lakefront Property",
        "price": "$600,000",
        "location": "Denver, CO",
        "bedrooms": 4,
        "bathrooms": 3,
        "size": "3,000 sq ft",
        "type": "Villa",
        "image": "https://c1.wallpaperflare.com/preview/551/3/749/architecture-family-house-front-yard-garage-thumbnail.jpg",
        "description": "A picturesque property with stunning lake views and private dock.",
        "year_built": 2017,
        "contact": "lakefront@homesale.com"
      }
    ]
  },
  {
    "id": 8,
    "location": "Miami, FL",
    "image": "https://e1.pxfuel.com/desktop-wallpaper/504/360/desktop-wallpaper-luxury-home-at-night-luxury-house-anime-thumbnail.jpg",
    "properties": [
      {
        "id": "A",
        "title": "Modern Family Home",
        "price": "$450,000",
        "location": "Miami, FL",
        "bedrooms": 4,
        "bathrooms": 3,
        "size": "2,800 sq ft",
        "type": "Single Family",
        "image": "https://e1.pxfuel.com/desktop-wallpaper/504/360/desktop-wallpaper-luxury-home-at-night-luxury-house-anime-thumbnail.jpg",
        "description": "A spacious family home with modern amenities, open floor plan, and a large backyard.",
        "year_built": 2018,
        "contact": "contact@homesale.com"
      },
      {
        "id": "B",
        "title": "Luxury Villa",
        "price": "$850,000",
        "location": "Miami, FL",
        "bedrooms": 5,
        "bathrooms": 4,
        "size": "3,500 sq ft",
        "type": "Villa",
        "image": "https://wallpapercat.com/w/full/0/2/8/743826-1920x1080-desktop-1080p-house-wallpaper.jpg",
        "description": "A beautiful villa with a stunning design, swimming pool, and prime location.",
        "year_built": 2020,
        "contact": "luxury@homesale.com"
      },
      {
        "id": "C",
        "title": "Cozy Cottage",
        "price": "$300,000",
        "location": "Miami, FL",
        "bedrooms": 3,
        "bathrooms": 2,
        "size": "1,800 sq ft",
        "type": "Cottage",
        "image": "https://e0.pxfuel.com/wallpapers/361/35/desktop-wallpaper-vintage-victorian-in-chelsea-that-was-cut-into-apartments-is-restored-old-homes.jpg",
        "description": "A charming cottage with vintage aesthetics and a large garden.",
        "year_built": 2015,
        "contact": "cozycottage@homesale.com"
      },
      {
        "id": "D",
        "title": "Urban Apartment",
        "price": "$200,000",
        "location": "Miami, FL",
        "bedrooms": 2,
        "bathrooms": 2,
        "size": "1,200 sq ft",
        "type": "Apartment",
        "image": "https://c1.wallpaperflare.com/preview/551/3/749/architecture-family-house-front-yard-garage-thumbnail.jpg",
        "description": "A modern apartment located in the heart of the city with all conveniences.",
        "year_built": 2021,
        "contact": "urban@homesale.com"
      },
      {
        "id": "E",
        "title": "Suburban House",
        "price": "$400,000",
        "location": "Miami, FL",
        "bedrooms": 4,
        "bathrooms": 3,
        "size": "2,500 sq ft",
        "type": "Single Family",
        "image": "https://media.istockphoto.com/id/488120139/photo/modern-real-estate.jpg?s=612x612&w=0&k=20&c=88jk1VLSoYboMmLUx173sHs_XrZ9pH21as8lC7WINQs=",
        "description": "A lovely suburban house with a spacious yard and modern kitchen.",
        "year_built": 2019,
        "contact": "suburban@homesale.com"
      },
      {
        "id": "F",
        "title": "Lakefront Property",
        "price": "$600,000",
        "location": "Miami, FL",
        "bedrooms": 4,
        "bathrooms": 3,
        "size": "3,000 sq ft",
        "type": "Villa",
        "image": "https://images.alphacoders.com/435/435117.jpg",
        "description": "A picturesque property with stunning lake views and private dock.",
        "year_built": 2017,
        "contact": "lakefront@homesale.com"
      }
    ]
  },
  {
    "id": 9,
    "location": "Orlando, FL",
    "image": "https://e0.pxfuel.com/wallpapers/19/156/desktop-wallpaper-modern-house-1920x1080-mansion-thumbnail.jpg",
    "properties": [
      {
        "id": "A",
        "title": "Modern Family Home",
        "price": "$450,000",
        "location": "Orlando, FL",
        "bedrooms": 4,
        "bathrooms": 3,
        "size": "2,800 sq ft",
        "type": "Single Family",
        "image": "https://e0.pxfuel.com/wallpapers/19/156/desktop-wallpaper-modern-house-1920x1080-mansion-thumbnail.jpg",
        "description": "A spacious family home with modern amenities, open floor plan, and a large backyard.",
        "year_built": 2018,
        "contact": "contact@homesale.com"
      },
      {
        "id": "B",
        "title": "Luxury Villa",
        "price": "$850,000",
        "location": "Orlando, FL",
        "bedrooms": 5,
        "bathrooms": 4,
        "size": "3,500 sq ft",
        "type": "Villa",
        "image": "https://e0.pxfuel.com/wallpapers/361/35/desktop-wallpaper-vintage-victorian-in-chelsea-that-was-cut-into-apartments-is-restored-old-homes.jpg",
        "description": "A beautiful villa with a stunning design, swimming pool, and prime location.",
        "year_built": 2020,
        "contact": "luxury@homesale.com"
      },
      {
        "id": "C",
        "title": "Cozy Cottage",
        "price": "$300,000",
        "location": "Orlando, FL",
        "bedrooms": 3,
        "bathrooms": 2,
        "size": "1,800 sq ft",
        "type": "Cottage",
        "image": "https://wallpapercat.com/w/full/0/2/8/743826-1920x1080-desktop-1080p-house-wallpaper.jpg",
        "description": "A charming cottage with vintage aesthetics and a large garden.",
        "year_built": 2015,
        "contact": "cozycottage@homesale.com"
      },
      {
        "id": "D",
        "title": "Urban Apartment",
        "price": "$200,000",
        "location": "Orlando, FL",
        "bedrooms": 2,
        "bathrooms": 2,
        "size": "1,200 sq ft",
        "type": "Apartment",
        "image": "https://media.istockphoto.com/id/488120139/photo/modern-real-estate.jpg?s=612x612&w=0&k=20&c=88jk1VLSoYboMmLUx173sHs_XrZ9pH21as8lC7WINQs=",
        "description": "A modern apartment located in the heart of the city with all conveniences.",
        "year_built": 2021,
        "contact": "urban@homesale.com"
      },
      {
        "id": "E",
        "title": "Suburban House",
        "price": "$400,000",
        "location": "Orlando, FL",
        "bedrooms": 4,
        "bathrooms": 3,
        "size": "2,500 sq ft",
        "type": "Single Family",
        "image": "https://images.alphacoders.com/435/435117.jpg",
        "description": "A lovely suburban house with a spacious yard and modern kitchen.",
        "year_built": 2019,
        "contact": "suburban@homesale.com"
      },
      {
        "id": "F",
        "title": "Lakefront Property",
        "price": "$600,000",
        "location": "Orlando, FL",
        "bedrooms": 4,
        "bathrooms": 3,
        "size": "3,000 sq ft",
        "type": "Villa",
        "image": "https://c1.wallpaperflare.com/preview/551/3/749/architecture-family-house-front-yard-garage-thumbnail.jpg",
        "description": "A picturesque property with stunning lake views and private dock.",
        "year_built": 2017,
        "contact": "lakefront@homesale.com"
      }
    ]
  },
  {
    "id": 10,
    "location": "Atlanta, GA",
    "image": "https://e0.pxfuel.com/wallpapers/439/104/desktop-wallpaper-malaysia-bungalow-house-27921-home-thumbnail.jpg",
    "properties": [
      {
        "id": "A",
        "title": "Modern Family Home",
        "price": "$450,000",
        "location": "Atlanta, GA",
        "bedrooms": 4,
        "bathrooms": 3,
        "size": "2,800 sq ft",
        "type": "Single Family",
        "image": "https://e0.pxfuel.com/wallpapers/439/104/desktop-wallpaper-malaysia-bungalow-house-27921-home-thumbnail.jpg",
        "description": "A spacious family home with modern amenities, open floor plan, and a large backyard.",
        "year_built": 2018,
        "contact": "contact@homesale.com"
      },
      {
        "id": "B",
        "title": "Luxury Villa",
        "price": "$850,000",
        "location": "Atlanta, GA",
        "bedrooms": 5,
        "bathrooms": 4,
        "size": "3,500 sq ft",
        "type": "Villa",
        "image": "https://c1.wallpaperflare.com/preview/551/3/749/architecture-family-house-front-yard-garage-thumbnail.jpg",
        "description": "A beautiful villa with a stunning design, swimming pool, and prime location.",
        "year_built": 2020,
        "contact": "luxury@homesale.com"
      },
      {
        "id": "C",
        "title": "Cozy Cottage",
        "price": "$300,000",
        "location": "Atlanta, GA",
        "bedrooms": 3,
        "bathrooms": 2,
        "size": "1,800 sq ft",
        "type": "Cottage",
        "image": "https://media.istockphoto.com/id/488120139/photo/modern-real-estate.jpg?s=612x612&w=0&k=20&c=88jk1VLSoYboMmLUx173sHs_XrZ9pH21as8lC7WINQs=",
        "description": "A charming cottage with vintage aesthetics and a large garden.",
        "year_built": 2015,
        "contact": "cozycottage@homesale.com"
      },
      {
        "id": "D",
        "title": "Urban Apartment",
        "price": "$200,000",
        "location": "Atlanta, GA",
        "bedrooms": 2,
        "bathrooms": 2,
        "size": "1,200 sq ft",
        "type": "Apartment",
        "image": "https://images.alphacoders.com/435/435117.jpg",
        "description": "A modern apartment located in the heart of the city with all conveniences.",
        "year_built": 2021,
        "contact": "urban@homesale.com"
      },
      {
        "id": "E",
        "title": "Suburban House",
        "price": "$400,000",
        "location": "Atlanta, GA",
        "bedrooms": 4,
        "bathrooms": 3,
        "size": "2,500 sq ft",
        "type": "Single Family",
        "image": "https://e0.pxfuel.com/wallpapers/361/35/desktop-wallpaper-vintage-victorian-in-chelsea-that-was-cut-into-apartments-is-restored-old-homes.jpg",
        "description": "A lovely suburban house with a spacious yard and modern kitchen.",
        "year_built": 2019,
        "contact": "suburban@homesale.com"
      },
      {
        "id": "F",
        "title": "Lakefront Property",
        "price": "$600,000",
        "location": "Atlanta, GA",
        "bedrooms": 4,
        "bathrooms": 3,
        "size": "3,000 sq ft",
        "type": "Villa",
        "image": "https://wallpapercat.com/w/full/0/2/8/743826-1920x1080-desktop-1080p-house-wallpaper.jpg",
        "description": "A picturesque property with stunning lake views and private dock.",
        "year_built": 2017,
        "contact": "lakefront@homesale.com"
      }
    ]
  },
  {
    "id": 11,
    "location": "Boston, MA",
    "image": "https://static.vecteezy.com/system/resources/thumbnails/026/586/024/small/beautiful-modern-house-exterior-with-carport-modern-residential-district-and-minimalist-building-concept-by-ai-generated-free-photo.jpg",
    "properties": [
      {
        "id": "A",
        "title": "Modern Family Home",
        "price": "$450,000",
        "location": "Boston, MA",
        "bedrooms": 4,
        "bathrooms": 3,
        "size": "2,800 sq ft",
        "type": "Single Family",
        "image": "https://static.vecteezy.com/system/resources/thumbnails/026/586/024/small/beautiful-modern-house-exterior-with-carport-modern-residential-district-and-minimalist-building-concept-by-ai-generated-free-photo.jpg",
        "description": "A spacious family home with modern amenities, open floor plan, and a large backyard.",
        "year_built": 2018,
        "contact": "contact@homesale.com"
      },
      {
        "id": "B",
        "title": "Luxury Villa",
        "price": "$850,000",
        "location": "Boston, MA",
        "bedrooms": 5,
        "bathrooms": 4,
        "size": "3,500 sq ft",
        "type": "Villa",
        "image": "https://c1.wallpaperflare.com/preview/551/3/749/architecture-family-house-front-yard-garage-thumbnail.jpg",
        "description": "A beautiful villa with a stunning design, swimming pool, and prime location.",
        "year_built": 2020,
        "contact": "luxury@homesale.com"
      },
      {
        "id": "C",
        "title": "Cozy Cottage",
        "price": "$300,000",
        "location": "Boston, MA",
        "bedrooms": 3,
        "bathrooms": 2,
        "size": "1,800 sq ft",
        "type": "Cottage",
        "image": "https://wallpapercat.com/w/full/0/2/8/743826-1920x1080-desktop-1080p-house-wallpaper.jpg",
        "description": "A charming cottage with vintage aesthetics and a large garden.",
        "year_built": 2015,
        "contact": "cozycottage@homesale.com"
      },
      {
        "id": "D",
        "title": "Urban Apartment",
        "price": "$200,000",
        "location": "Boston, MA",
        "bedrooms": 2,
        "bathrooms": 2,
        "size": "1,200 sq ft",
        "type": "Apartment",
        "image": "https://e0.pxfuel.com/wallpapers/361/35/desktop-wallpaper-vintage-victorian-in-chelsea-that-was-cut-into-apartments-is-restored-old-homes.jpg",
        "description": "A modern apartment located in the heart of the city with all conveniences.",
        "year_built": 2021,
        "contact": "urban@homesale.com"
      },
      {
        "id": "E",
        "title": "Suburban House",
        "price": "$400,000",
        "location": "Boston, MA",
        "bedrooms": 4,
        "bathrooms": 3,
        "size": "2,500 sq ft",
        "type": "Single Family",
        "image": "https://images.alphacoders.com/435/435117.jpg",
        "description": "A lovely suburban house with a spacious yard and modern kitchen.",
        "year_built": 2019,
        "contact": "suburban@homesale.com"
      },
      {
        "id": "F",
        "title": "Lakefront Property",
        "price": "$600,000",
        "location": "Boston, MA",
        "bedrooms": 4,
        "bathrooms": 3,
        "size": "3,000 sq ft",
        "type": "Villa",
        "image": "https://media.istockphoto.com/id/488120139/photo/modern-real-estate.jpg?s=612x612&w=0&k=20&c=88jk1VLSoYboMmLUx173sHs_XrZ9pH21as8lC7WINQs=",
        "description": "A picturesque property with stunning lake views and private dock.",
        "year_built": 2017,
        "contact": "lakefront@homesale.com"
      }
    ]
  },
  {
    "id": 12,
    "location": "Las Vegas, NV",
    "image": "https://wallpapercat.com/w/full/0/2/8/743826-1920x1080-desktop-1080p-house-wallpaper.jpg",
    "properties": [
      {
        "id": "A",
        "title": "Modern Family Home",
        "price": "$450,000",
        "location": "Las Vegas, NV",
        "bedrooms": 4,
        "bathrooms": 3,
        "size": "2,800 sq ft",
        "type": "Single Family",
        "image": "https://wallpapercat.com/w/full/0/2/8/743826-1920x1080-desktop-1080p-house-wallpaper.jpg",
        "description": "A spacious family home with modern amenities, open floor plan, and a large backyard.",
        "year_built": 2018,
        "contact": "contact@homesale.com"
      },
      {
        "id": "B",
        "title": "Luxury Villa",
        "price": "$850,000",
        "location": "Las Vegas, NV",
        "bedrooms": 5,
        "bathrooms": 4,
        "size": "3,500 sq ft",
        "type": "Villa",
        "image": "https://c1.wallpaperflare.com/preview/551/3/749/architecture-family-house-front-yard-garage-thumbnail.jpg",
        "description": "A beautiful villa with a stunning design, swimming pool, and prime location.",
        "year_built": 2020,
        "contact": "luxury@homesale.com"
      },
      {
        "id": "C",
        "title": "Cozy Cottage",
        "price": "$300,000",
        "location": "Las Vegas, NV",
        "bedrooms": 3,
        "bathrooms": 2,
        "size": "1,800 sq ft",
        "type": "Cottage",
        "image": "https://media.istockphoto.com/id/488120139/photo/modern-real-estate.jpg?s=612x612&w=0&k=20&c=88jk1VLSoYboMmLUx173sHs_XrZ9pH21as8lC7WINQs=",
        "description": "A charming cottage with vintage aesthetics and a large garden.",
        "year_built": 2015,
        "contact": "cozycottage@homesale.com"
      },
      {
        "id": "D",
        "title": "Urban Apartment",
        "price": "$200,000",
        "location": "Las Vegas, NV",
        "bedrooms": 2,
        "bathrooms": 2,
        "size": "1,200 sq ft",
        "type": "Apartment",
        "image": "https://images.alphacoders.com/435/435117.jpg",
        "description": "A modern apartment located in the heart of the city with all conveniences.",
        "year_built": 2021,
        "contact": "urban@homesale.com"
      },
      {
        "id": "E",
        "title": "Suburban House",
        "price": "$400,000",
        "location": "Las Vegas, NV",
        "bedrooms": 4,
        "bathrooms": 3,
        "size": "2,500 sq ft",
        "type": "Single Family",
        "image": "https://e1.pxfuel.com/desktop-wallpaper/504/360/desktop-wallpaper-luxury-home-at-night-luxury-house-anime-thumbnail.jpg",
        "description": "A lovely suburban house with a spacious yard and modern kitchen.",
        "year_built": 2019,
        "contact": "suburban@homesale.com"
      },
      {
        "id": "F",
        "title": "Lakefront Property",
        "price": "$600,000",
        "location": "Las Vegas, NV",
        "bedrooms": 4,
        "bathrooms": 3,
        "size": "3,000 sq ft",
        "type": "Villa",
        "image": "https://e0.pxfuel.com/wallpapers/361/35/desktop-wallpaper-vintage-victorian-in-chelsea-that-was-cut-into-apartments-is-restored-old-homes.jpg",
        "description": "A picturesque property with stunning lake views and private dock.",
        "year_built": 2017,
        "contact": "lakefront@homesale.com"
      }
    ]
  },
  {
    "id": 13,
    "location": "Phoenix, AZ",
    "image": "https://static.vecteezy.com/system/resources/thumbnails/029/698/014/small_2x/beautiful-white-lightening-house-exterior-with-stairs-road-decorated-flowers-and-grass-ai-generative-photo.jpg",
    "properties": [
      {
        "id": "A",
        "title": "Modern Family Home",
        "price": "$450,000",
        "location": "Phoenix, AZ",
        "bedrooms": 4,
        "bathrooms": 3,
        "size": "2,800 sq ft",
        "type": "Single Family",
        "image": "https://static.vecteezy.com/system/resources/thumbnails/029/698/014/small_2x/beautiful-white-lightening-house-exterior-with-stairs-road-decorated-flowers-and-grass-ai-generative-photo.jpg",
        "description": "A spacious family home with modern amenities, open floor plan, and a large backyard.",
        "year_built": 2018,
        "contact": "contact@homesale.com"
      },
      {
        "id": "B",
        "title": "Luxury Villa",
        "price": "$850,000",
        "location": "Phoenix, AZ",
        "bedrooms": 5,
        "bathrooms": 4,
        "size": "3,500 sq ft",
        "type": "Villa",
        "image": "https://wallpapercat.com/w/full/0/2/8/743826-1920x1080-desktop-1080p-house-wallpaper.jpg",
        "description": "A beautiful villa with a stunning design, swimming pool, and prime location.",
        "year_built": 2020,
        "contact": "luxury@homesale.com"
      },
      {
        "id": "C",
        "title": "Cozy Cottage",
        "price": "$300,000",
        "location": "Phoenix, AZ",
        "bedrooms": 3,
        "bathrooms": 2,
        "size": "1,800 sq ft",
        "type": "Cottage",
        "image": "https://e0.pxfuel.com/wallpapers/361/35/desktop-wallpaper-vintage-victorian-in-chelsea-that-was-cut-into-apartments-is-restored-old-homes.jpg",
        "description": "A charming cottage with vintage aesthetics and a large garden.",
        "year_built": 2015,
        "contact": "cozycottage@homesale.com"
      },
      {
        "id": "D",
        "title": "Urban Apartment",
        "price": "$200,000",
        "location": "Phoenix, AZ",
        "bedrooms": 2,
        "bathrooms": 2,
        "size": "1,200 sq ft",
        "type": "Apartment",
        "image": "https://media.istockphoto.com/id/488120139/photo/modern-real-estate.jpg?s=612x612&w=0&k=20&c=88jk1VLSoYboMmLUx173sHs_XrZ9pH21as8lC7WINQs=",
        "description": "A modern apartment located in the heart of the city with all conveniences.",
        "year_built": 2021,
        "contact": "urban@homesale.com"
      },
      {
        "id": "E",
        "title": "Suburban House",
        "price": "$400,000",
        "location": "Phoenix, AZ",
        "bedrooms": 4,
        "bathrooms": 3,
        "size": "2,500 sq ft",
        "type": "Single Family",
        "image": "https://c1.wallpaperflare.com/preview/551/3/749/architecture-family-house-front-yard-garage-thumbnail.jpg",
        "description": "A lovely suburban house with a spacious yard and modern kitchen.",
        "year_built": 2019,
        "contact": "suburban@homesale.com"
      },
      {
        "id": "F",
        "title": "Lakefront Property",
        "price": "$600,000",
        "location": "Phoenix, AZ",
        "bedrooms": 4,
        "bathrooms": 3,
        "size": "3,000 sq ft",
        "type": "Villa",
        "image": "https://images.alphacoders.com/435/435117.jpg",
        "description": "A picturesque property with stunning lake views and private dock.",
        "year_built": 2017,
        "contact": "lakefront@homesale.com"
      }
    ]
  }
]